setup.py
kambo/__init__.py
kambo.egg-info/PKG-INFO
kambo.egg-info/SOURCES.txt
kambo.egg-info/dependency_links.txt
kambo.egg-info/top_level.txt