Metadata-Version: 1.1
Name: kambo
Version: 0.1
Summary: Kambo web framework
Home-page: UNKNOWN
Author: Ilya Strukov
Author-email: iley@iley.ru
License: UNKNOWN
Platform: UNKNOWN
Classifier: Development Status :: 1 - Planning
Classifier: Programming Language :: Python :: 3.3
